setup.py
bin/check_springboot
check_springboot/__init__.py
check_springboot.egg-info/PKG-INFO
check_springboot.egg-info/SOURCES.txt
check_springboot.egg-info/dependency_links.txt
check_springboot.egg-info/not-zip-safe
check_springboot.egg-info/requires.txt
check_springboot.egg-info/top_level.txt